{"EntityKeyName":"long","EntityDisplayName":null,"BaseClassName":"FullAuditedEntity<long>","BaseClassDtoName":"FullAuditedEntityDto<long>","BaseClassNameList":"","Name":"BookResource","LowerName":"bookResource","SplitName":"book-resource","NameSplit":["book","resource"],"Namespace":"U_StudyingCommunity_Dream.Books","Properties":[{"Checked":true,"EditChecked":true,"ListChecked":true,"FieldName":"BookId","FieldDisplayName":"BookId","Required":false,"MinLength":null,"MaxLength":null,"RegularExpression":null,"FieldTypeStr":"long","FieldType":null,"CtrlTypes":["Text","Checkbox","Textarea","DatePicker","DateTimePicker","DropdownList"],"CtrlTypeIndex":0,"IsCollection":false,"FieldNameFirstLower":"bookId","ContrlType":"Text","AttributesList":[],"IsSimpleProperty":true,"IsRelation":false,"RelatedEntityName":null},{"Checked":true,"EditChecked":true,"ListChecked":true,"FieldName":"Url","FieldDisplayName":"Url","Required":true,"MinLength":null,"MaxLength":null,"RegularExpression":null,"FieldTypeStr":"string","FieldType":null,"CtrlTypes":["Text","Checkbox","Textarea","DatePicker","DateTimePicker","DropdownList"],"CtrlTypeIndex":0,"IsCollection":false,"FieldNameFirstLower":"url","ContrlType":"Text","AttributesList":["[Required]","[StringLength(200)]"],"IsSimpleProperty":true,"IsRelation":false,"RelatedEntityName":null},{"Checked":true,"EditChecked":true,"ListChecked":true,"FieldName":"Name","FieldDisplayName":"Name","Required":true,"MinLength":null,"MaxLength":null,"RegularExpression":null,"FieldTypeStr":"string","FieldType":null,"CtrlTypes":["Text","Checkbox","Textarea","DatePicker","DateTimePicker","DropdownList"],"CtrlTypeIndex":0,"IsCollection":false,"FieldNameFirstLower":"name","ContrlType":"Text","AttributesList":["[Required]","[StringLength(100)]"],"IsSimpleProperty":true,"IsRelation":false,"RelatedEntityName":null},{"Checked":true,"EditChecked":true,"ListChecked":true,"FieldName":"Uploader","FieldDisplayName":"Uploader","Required":false,"MinLength":null,"MaxLength":null,"RegularExpression":null,"FieldTypeStr":"Guid?","FieldType":null,"CtrlTypes":["Text","Checkbox","Textarea","DatePicker","DateTimePicker","DropdownList"],"CtrlTypeIndex":0,"IsCollection":false,"FieldNameFirstLower":"uploader","ContrlType":"Text","AttributesList":[],"IsSimpleProperty":true,"IsRelation":false,"RelatedEntityName":null},{"Checked":true,"EditChecked":true,"ListChecked":true,"FieldName":"Auditor","FieldDisplayName":"Auditor","Required":false,"MinLength":null,"MaxLength":null,"RegularExpression":null,"FieldTypeStr":"Guid?","FieldType":null,"CtrlTypes":["Text","Checkbox","Textarea","DatePicker","DateTimePicker","DropdownList"],"CtrlTypeIndex":0,"IsCollection":false,"FieldNameFirstLower":"auditor","ContrlType":"Text","AttributesList":[],"IsSimpleProperty":true,"IsRelation":false,"RelatedEntityName":null},{"Checked":true,"EditChecked":true,"ListChecked":true,"FieldName":"Status","FieldDisplayName":"Status","Required":false,"MinLength":null,"MaxLength":null,"RegularExpression":null,"FieldTypeStr":"BookResourceStatus","FieldType":null,"CtrlTypes":["Text","Checkbox","Textarea","DatePicker","DateTimePicker","DropdownList"],"CtrlTypeIndex":0,"IsCollection":false,"FieldNameFirstLower":"status","ContrlType":"Text","AttributesList":[],"IsSimpleProperty":false,"IsRelation":true,"RelatedEntityName":null}]}